{
  "version": 1,
  "createdAt": "2026-06-16T02:08:28.416Z",
  "updatedAt": "2026-06-16T02:19:24.136Z",
  "briefPath": ".omx/ultragoal/brief.md",
  "goalsPath": ".omx/ultragoal/goals.json",
  "ledgerPath": ".omx/ultragoal/ledger.jsonl",
  "codexGoalMode": "aggregate",
  "goals": [
    {
      "id": "G001-crates-storage-src-appdb-rs-encrypte",
      "title": "`crates/storage/src/appdb.rs`: encrypted app DB envelope, schema mani...",
      "objective": "`crates/storage/src/appdb.rs`: encrypted app DB envelope, schema manifest, migration planner, corrupt-store quarantine helper.",
      "status": "complete",
      "attempt": 1,
      "createdAt": "2026-06-16T02:08:28.416Z",
      "updatedAt": "2026-06-16T02:11:06.228Z",
      "startedAt": "2026-06-16T02:08:39.852Z",
      "completedAt": "2026-06-16T02:11:06.228Z",
      "evidence": "Inspected crates/storage/src/appdb.rs encrypted envelope, migration planner, and quarantine helper; no storage-crate behavior change needed for P1-T01 desktop app-state schema handling."
    },
    {
      "id": "G002-apps-desktop-src-tauri-src-lib-rs-ty",
      "title": "`apps/desktop/src-tauri/src/lib.rs`: typed app-state schema, load/per...",
      "objective": "`apps/desktop/src-tauri/src/lib.rs`: typed app-state schema, load/persist behavior, storage security UI state.",
      "status": "complete",
      "attempt": 0,
      "createdAt": "2026-06-16T02:08:28.416Z",
      "updatedAt": "2026-06-16T02:16:56.278Z",
      "completedAt": "2026-06-16T02:16:56.278Z",
      "evidence": "Implemented desktop typed app-state schema load/persist changes in apps/desktop/src-tauri/src/lib.rs."
    },
    {
      "id": "G003-missing-schema-version-is-treated-as",
      "title": "Missing `schema_version` is treated as an explicit legacy app-state m...",
      "objective": "Missing `schema_version` is treated as an explicit legacy app-state migration to schema 1 and persists the migrated version only after successful decode.",
      "status": "complete",
      "attempt": 0,
      "createdAt": "2026-06-16T02:08:28.416Z",
      "updatedAt": "2026-06-16T02:16:56.631Z",
      "completedAt": "2026-06-16T02:16:56.631Z",
      "evidence": "Missing schema_version is classified as legacy version 0, decoded, normalized to schema 1, and persisted only after successful decode; regression test passed."
    },
    {
      "id": "G004-old-supported-app-state-schema-versi",
      "title": "Old supported app-state schema versions migrate by explicit rule.",
      "objective": "Old supported app-state schema versions migrate by explicit rule.",
      "status": "complete",
      "attempt": 0,
      "createdAt": "2026-06-16T02:08:28.416Z",
      "updatedAt": "2026-06-16T02:16:56.950Z",
      "completedAt": "2026-06-16T02:16:56.950Z",
      "evidence": "Explicit schema_version 0 migrates to current schema 1 by rule; regression test passed."
    },
    {
      "id": "G005-future-unsupported-schema-versions-f",
      "title": "Future/unsupported schema versions fail closed with a typed persisten...",
      "objective": "Future/unsupported schema versions fail closed with a typed persistence error and recovery hint.",
      "status": "complete",
      "attempt": 0,
      "createdAt": "2026-06-16T02:08:28.416Z",
      "updatedAt": "2026-06-16T02:17:17.200Z",
      "completedAt": "2026-06-16T02:17:17.200Z",
      "evidence": "Future schema versions return state_schema_future and do not overwrite existing bytes; regression test passed."
    },
    {
      "id": "G006-corrupt-unreadable-state-fails-close",
      "title": "Corrupt/unreadable state fails closed with a typed persistence error;...",
      "objective": "Corrupt/unreadable state fails closed with a typed persistence error; the existing bytes remain preserved.",
      "status": "complete",
      "attempt": 0,
      "createdAt": "2026-06-16T02:08:28.416Z",
      "updatedAt": "2026-06-16T02:17:17.537Z",
      "completedAt": "2026-06-16T02:17:17.537Z",
      "evidence": "Corrupt JSON returns state_decode_failed and leaves original bytes intact; regression test passed."
    },
    {
      "id": "G007-regression-tests-cover-missing-schem",
      "title": "Regression tests cover missing schema version, old store, corrupt sto...",
      "objective": "Regression tests cover missing schema version, old store, corrupt store preservation, and future-version rejection.",
      "status": "complete",
      "attempt": 0,
      "createdAt": "2026-06-16T02:08:28.416Z",
      "updatedAt": "2026-06-16T02:17:17.875Z",
      "completedAt": "2026-06-16T02:17:17.875Z",
      "evidence": "Added/updated regression tests for missing schema_version, explicit old schema_version 0, corrupt bytes preservation, and future schema rejection; all targeted tests passed."
    },
    {
      "id": "G008-add-a-small-schema-version-classifie",
      "title": "Add a small schema-version classifier around raw persisted JSON in `a...",
      "objective": "Add a small schema-version classifier around raw persisted JSON in `apps/desktop/src-tauri/src/lib.rs` before deserializing with serde defaults.",
      "status": "complete",
      "attempt": 0,
      "createdAt": "2026-06-16T02:08:28.416Z",
      "updatedAt": "2026-06-16T02:17:18.224Z",
      "completedAt": "2026-06-16T02:17:18.224Z",
      "evidence": "Added persisted_schema_version classifier before serde defaults can hide missing schema_version."
    },
    {
      "id": "G009-replace-the-broad-schema-mismatch-br",
      "title": "Replace the broad schema mismatch branch with explicit current, legac...",
      "objective": "Replace the broad schema mismatch branch with explicit current, legacy-migrate, unsupported-old, and future-version outcomes.",
      "status": "complete",
      "attempt": 0,
      "createdAt": "2026-06-16T02:08:28.416Z",
      "updatedAt": "2026-06-16T02:17:39.078Z",
      "completedAt": "2026-06-16T02:17:39.078Z",
      "evidence": "Replaced broad schema mismatch branch with explicit current, legacy migration, future, invalid, and decode-failed outcomes."
    },
    {
      "id": "G010-persist-migrated-legacy-state-throug",
      "title": "Persist migrated legacy state through the existing `AppStore` only af...",
      "objective": "Persist migrated legacy state through the existing `AppStore` only after successful decode and normalization.",
      "status": "complete",
      "attempt": 0,
      "createdAt": "2026-06-16T02:08:28.416Z",
      "updatedAt": "2026-06-16T02:17:39.424Z",
      "completedAt": "2026-06-16T02:17:39.424Z",
      "evidence": "Legacy app state is persisted through AppStore after successful decode/normalization; save failure is surfaced in last_command_error."
    },
    {
      "id": "G011-add-targeted-desktop-unit-tests-for",
      "title": "Add targeted desktop unit tests for missing schema, old schema, corru...",
      "objective": "Add targeted desktop unit tests for missing schema, old schema, corrupt bytes preservation, and future schema rejection.",
      "status": "complete",
      "attempt": 0,
      "createdAt": "2026-06-16T02:08:28.416Z",
      "updatedAt": "2026-06-16T02:17:39.725Z",
      "completedAt": "2026-06-16T02:17:39.725Z",
      "evidence": "Added targeted desktop unit tests for missing schema, explicit old schema, corrupt preservation, and future rejection."
    },
    {
      "id": "G012-run-focused-rust-tests-for-the-deskt",
      "title": "Run focused Rust tests for the desktop persistence path and storage a...",
      "objective": "Run focused Rust tests for the desktop persistence path and storage app DB tests; run format check if toolchain availability allows.",
      "status": "complete",
      "attempt": 0,
      "createdAt": "2026-06-16T02:08:28.416Z",
      "updatedAt": "2026-06-16T02:17:40.051Z",
      "completedAt": "2026-06-16T02:17:40.051Z",
      "evidence": "Ran cargo fmt --check plus targeted desktop persistence tests and discrypt-storage appdb tests with local Rust 1.89.0 toolchain; all passed."
    },
    {
      "id": "G013-corrupt-json-do-not-write-delete-or",
      "title": "Corrupt JSON: do not write, delete, or rename the store in the deskto...",
      "objective": "Corrupt JSON: do not write, delete, or rename the store in the desktop loader; surface `state_decode_failed`.",
      "status": "complete",
      "attempt": 0,
      "createdAt": "2026-06-16T02:08:28.416Z",
      "updatedAt": "2026-06-16T02:17:59.249Z",
      "completedAt": "2026-06-16T02:17:59.249Z",
      "evidence": "Corrupt JSON branch does not write, delete, or rename the store; test asserts byte preservation."
    },
    {
      "id": "G014-future-schema-do-not-downgrade-or-ov",
      "title": "Future schema: do not downgrade or overwrite; surface `state_schema_f...",
      "objective": "Future schema: do not downgrade or overwrite; surface `state_schema_future`.",
      "status": "complete",
      "attempt": 0,
      "createdAt": "2026-06-16T02:08:28.416Z",
      "updatedAt": "2026-06-16T02:17:59.552Z",
      "completedAt": "2026-06-16T02:17:59.552Z",
      "evidence": "Future schema branch returns state_schema_future and preserves bytes for newer builds."
    },
    {
      "id": "G015-legacy-schema-decode-failure-do-not",
      "title": "Legacy schema decode failure: do not overwrite; surface `state_decode...",
      "objective": "Legacy schema decode failure: do not overwrite; surface `state_decode_failed`.",
      "status": "complete",
      "attempt": 0,
      "createdAt": "2026-06-16T02:08:28.416Z",
      "updatedAt": "2026-06-16T02:17:59.861Z",
      "completedAt": "2026-06-16T02:17:59.861Z",
      "evidence": "Legacy decode failures route through state_decode_failed before any migration write; corrupt-state preservation test covers unreadable bytes."
    },
    {
      "id": "G016-legacy-migration-save-failure-load-t",
      "title": "Legacy migration save failure: load the migrated state but surface th...",
      "objective": "Legacy migration save failure: load the migrated state but surface the save error so the UI does not claim persistence.",
      "status": "complete",
      "attempt": 0,
      "createdAt": "2026-06-16T02:08:28.416Z",
      "updatedAt": "2026-06-16T02:18:00.193Z",
      "completedAt": "2026-06-16T02:18:00.193Z",
      "evidence": "Legacy migration save errors are assigned to last_command_error after normalized state load, avoiding a false persistence claim."
    },
    {
      "id": "G017-rustup-toolchain-1-89-0-cargo-test-m",
      "title": "`RUSTUP_TOOLCHAIN=1.89.0 cargo test --manifest-path apps/desktop/src-...",
      "objective": "`RUSTUP_TOOLCHAIN=1.89.0 cargo test --manifest-path apps/desktop/src-tauri/Cargo.toml persisted_state_without_schema_version_migrates_to_current_schema`",
      "status": "complete",
      "attempt": 0,
      "createdAt": "2026-06-16T02:08:28.416Z",
      "updatedAt": "2026-06-16T02:18:21.831Z",
      "completedAt": "2026-06-16T02:18:21.831Z",
      "evidence": "Passed: RUSTUP_TOOLCHAIN=1.89.0 cargo test --manifest-path apps/desktop/src-tauri/Cargo.toml persisted_state_without_schema_version_migrates_to_current_schema"
    },
    {
      "id": "G018-rustup-toolchain-1-89-0-cargo-test-m",
      "title": "`RUSTUP_TOOLCHAIN=1.89.0 cargo test --manifest-path apps/desktop/src-...",
      "objective": "`RUSTUP_TOOLCHAIN=1.89.0 cargo test --manifest-path apps/desktop/src-tauri/Cargo.toml persisted_old_schema_version_migrates_to_current_schema`",
      "status": "complete",
      "attempt": 0,
      "createdAt": "2026-06-16T02:08:28.416Z",
      "updatedAt": "2026-06-16T02:18:22.205Z",
      "completedAt": "2026-06-16T02:18:22.205Z",
      "evidence": "Passed: RUSTUP_TOOLCHAIN=1.89.0 cargo test --manifest-path apps/desktop/src-tauri/Cargo.toml persisted_old_schema_version_migrates_to_current_schema"
    },
    {
      "id": "G019-rustup-toolchain-1-89-0-cargo-test-m",
      "title": "`RUSTUP_TOOLCHAIN=1.89.0 cargo test --manifest-path apps/desktop/src-...",
      "objective": "`RUSTUP_TOOLCHAIN=1.89.0 cargo test --manifest-path apps/desktop/src-tauri/Cargo.toml corrupt_persisted_state_surfaces_recovery_error_instead_of_silent_first_run`",
      "status": "complete",
      "attempt": 0,
      "createdAt": "2026-06-16T02:08:28.416Z",
      "updatedAt": "2026-06-16T02:18:22.501Z",
      "completedAt": "2026-06-16T02:18:22.501Z",
      "evidence": "Passed: RUSTUP_TOOLCHAIN=1.89.0 cargo test --manifest-path apps/desktop/src-tauri/Cargo.toml corrupt_persisted_state_surfaces_recovery_error_instead_of_silent_first_run and future_schema_version_fails_closed_without_overwriting_store"
    },
    {
      "id": "G020-rustup-toolchain-1-89-0-cargo-test-p",
      "title": "`RUSTUP_TOOLCHAIN=1.89.0 cargo test -p discrypt-storage appdb`",
      "objective": "`RUSTUP_TOOLCHAIN=1.89.0 cargo test -p discrypt-storage appdb`",
      "status": "review_blocked",
      "attempt": 1,
      "createdAt": "2026-06-16T02:08:28.416Z",
      "updatedAt": "2026-06-16T02:19:24.136Z",
      "startedAt": "2026-06-16T02:19:12.770Z",
      "reviewBlockedAt": "2026-06-16T02:19:24.136Z",
      "evidence": "Verification passed, but omx agents list --json returned 'No native agents found.', so required independent code-reviewer/architect final gate cannot run in this runtime."
    },
    {
      "id": "G021-independent-final-review-unavailable",
      "title": "Independent final review unavailable",
      "objective": "Run independent code-reviewer and architect review lanes for P1-T01 storage schema changes, then checkpoint the final Ultragoal gate if both lanes are clean.",
      "status": "pending",
      "attempt": 0,
      "createdAt": "2026-06-16T02:19:24.137Z",
      "updatedAt": "2026-06-16T02:19:24.137Z",
      "evidence": "Verification passed, but omx agents list --json returned 'No native agents found.', so required independent code-reviewer/architect final gate cannot run in this runtime."
    }
  ],
  "codexObjective": "Complete the durable ultragoal plan in .omx/ultragoal/goals.json, including later accepted/appended stories, under the original brief constraints; use .omx/ultragoal/ledger.jsonl as the audit trail."
}
